ssq.cpython-310-darwin.so
include/ssq/fftw_wrapper.hpp
include/ssq/wavelet.hpp
include/ssq/fsst.hpp
include/ssq/cwt.hpp
include/ssq/stft.hpp
include/ssq/wsst.hpp
include/ssq/constants.hpp
include/ssq/windows.hpp
include/ssq/types.hpp
ssq.dylibs/libfftw3.3.dylib
ssq-0.1.0.dist-info/RECORD
ssq-0.1.0.dist-info/WHEEL
ssq-0.1.0.dist-info/METADATA
ssq-0.1.0.dist-info/licenses/LICENSE
lib/libssq_core.a
