Metadata-Version: 2.4
Name: ssq
Version: 0.1.0
Summary: Synchrosqueezed Transform library (FSST and WSST)
Author-Email: Alvaro Gaona <alvgaona@gmail.com>
License-Expression: LGPL-3.0-or-later
Classifier: Development Status :: 4 - Beta
Classifier: Programming Language :: Python :: 3
Classifier: Programming Language :: Python :: 3.9
Classifier: Programming Language :: Python :: 3.10
Classifier: Programming Language :: Python :: 3.11
Classifier: Programming Language :: Python :: 3.12
Classifier: Programming Language :: Python :: 3.13
Classifier: Programming Language :: C++
Classifier: Topic :: Scientific/Engineering
Project-URL: Homepage, https://github.com/alvgaona/ssq
Project-URL: Repository, https://github.com/alvgaona/ssq
Requires-Python: >=3.9
